dict_sourcer-0.3.0.dist-info/METADATA
dict_sourcer-0.3.0.dist-info/WHEEL
dict_sourcer-0.3.0.dist-info/licenses/LICENSE
dict_sourcer/__pycache__/__init__.cpython-311.pyc
dict_sourcer/dict_sourcer.pyi
dict_sourcer/__init__.py
dict_sourcer/dict_sourcer.cpython-311-x86_64-linux-gnu.so
dict_sourcer-0.3.0.dist-info/RECORD
