Metadata-Version: 2.4
Name: dict_sourcer
Version: 0.3.0
License-File: LICENSE
Summary: A Python package for reducing mapping-like objects using reducer objects, implemented in Rust.
Author: Risto Kowaczewski
License: MIT
Requires-Python: >=3.6
